huaweicloudsdksmn/__init__.py
huaweicloudsdksmn/v2/__init__.py
huaweicloudsdksmn/v2/smn_async_client.py
huaweicloudsdksmn/v2/smn_client.py
huaweicloudsdksmn/v2/model/__init__.py
huaweicloudsdksmn/v2/model/add_kms_key_request_body.py
huaweicloudsdksmn/v2/model/add_subscription_from_subscription_user_request.py
huaweicloudsdksmn/v2/model/add_subscription_from_subscription_user_request_body.py
huaweicloudsdksmn/v2/model/add_subscription_from_subscription_user_response.py
huaweicloudsdksmn/v2/model/add_subscription_from_subscription_user_response_item.py
huaweicloudsdksmn/v2/model/add_subscription_request.py
huaweicloudsdksmn/v2/model/add_subscription_request_body.py
huaweicloudsdksmn/v2/model/add_subscription_response.py
huaweicloudsdksmn/v2/model/application_endpoint.py
huaweicloudsdksmn/v2/model/application_item.py
huaweicloudsdksmn/v2/model/batch_add_subscriptions_request_body.py
huaweicloudsdksmn/v2/model/batch_create_or_delete_resource_tags_request.py
huaweicloudsdksmn/v2/model/batch_create_or_delete_resource_tags_request_body.py
huaweicloudsdksmn/v2/model/batch_create_or_delete_resource_tags_response.py
huaweicloudsdksmn/v2/model/batch_create_subscriptions_filter_polices_request.py
huaweicloudsdksmn/v2/model/batch_create_subscriptions_filter_polices_response.py
huaweicloudsdksmn/v2/model/batch_delete_subscriptions_by_topic_request.py
huaweicloudsdksmn/v2/model/batch_delete_subscriptions_by_topic_response.py
huaweicloudsdksmn/v2/model/batch_delete_subscriptions_filter_polices_request.py
huaweicloudsdksmn/v2/model/batch_delete_subscriptions_filter_polices_request_body.py
huaweicloudsdksmn/v2/model/batch_delete_subscriptions_filter_polices_response.py
huaweicloudsdksmn/v2/model/batch_delete_subscriptions_request.py
huaweicloudsdksmn/v2/model/batch_delete_subscriptions_request_body.py
huaweicloudsdksmn/v2/model/batch_delete_subscriptions_request_item_info.py
huaweicloudsdksmn/v2/model/batch_delete_subscriptions_response.py
huaweicloudsdksmn-3.1.184.dist-info/METADATA
huaweicloudsdksmn-3.1.184.dist-info/WHEEL
huaweicloudsdksmn-3.1.184.dist-info/licenses/LICENSE
huaweicloudsdksmn-3.1.184.dist-info/RECORD
